meteofr/__about__.py
meteofr/__init__.py
meteofr/get_data.py
meteofr-0.0.6.dist-info/METADATA
meteofr-0.0.6.dist-info/WHEEL
meteofr-0.0.6.dist-info/licenses/LICENSE.txt
meteofr-0.0.6.dist-info/RECORD
