Metadata-Version: 2.4
Name: meteofr
Version: 0.0.6
Summary: Access Meteo France API to fetch weather data.
Project-URL: Documentation, https://github.com/goodfr/meteofr#readme
Project-URL: Issues, https://github.com/goodfr/meteofr/issues
Project-URL: Source, https://github.com/goodfr/meteofr
Author-email: goodfr <44895259+goodfr@users.noreply.github.com>
License-Expression: MIT
License-File: LICENSE.txt
Classifier: Development Status :: 4 - Beta
Classifier: Programming Language :: Python
Classifier: Programming Language :: Python :: 3.8
Classifier: Programming Language :: Python :: 3.9
Classifier: Programming Language :: Python :: 3.10
Classifier: Programming Language :: Python :: 3.11
Classifier: Programming Language :: Python :: 3.12
Classifier: Programming Language :: Python :: Implementation :: CPython
Classifier: Programming Language :: Python :: Implementation :: PyPy
Requires-Python: >=3.8
Requires-Dist: joblib>=1.4.2
Requires-Dist: numba>=0.58.1
Requires-Dist: pandas>=2.0.3
Requires-Dist: pytest>=8.3.5
Requires-Dist: requests>=2.32.3
Requires-Dist: tqdm>=4.67.1
